navernewscrawler/__init__.py
navernewscrawler/main.py
navernewscrawler/naver_crawler.py
navernewscrawler-0.0.3.dist-info/LICENSE.txt
navernewscrawler-0.0.3.dist-info/METADATA
navernewscrawler-0.0.3.dist-info/WHEEL
navernewscrawler-0.0.3.dist-info/entry_points.txt
navernewscrawler-0.0.3.dist-info/top_level.txt
navernewscrawler-0.0.3.dist-info/RECORD
