Metadata-Version: 2.1
Name: navernewscrawler
Version: 0.0.3
Summary: Tool for crawling news on Naver
Home-page: https://github.com/ehsong/navernewscrawler
Author: ['Eunhou Esther Song']
Author-email: eunhou.song@gmail.com
License: MIT
Platform: UNKNOWN
Requires-Dist: bs4
Requires-Dist: requests
